clusim/__init__.py
clusim/clugen.py
clusim/clusimelement.py
clusim/clustering.py
clusim/clusteringerror.py
clusim/dag.py
clusim/sim.py
clusim-0.4.dist-info/LICENSE
clusim-0.4.dist-info/METADATA
clusim-0.4.dist-info/WHEEL
clusim-0.4.dist-info/top_level.txt
clusim-0.4.dist-info/RECORD
