Metadata-Version: 2.1
Name: clusim
Version: 0.4
Summary: Clustering simliarity
Home-page: https://github.com/Hoosier-Clusters/clusim
Author: Alexander Gates <ajgates42@gmail.com>
Author-email: UNKNOWN
License: MIT
Keywords: clustering cluster comparison similarity data science network science network community
Platform: UNKNOWN
Classifier: Development Status :: 4 - Beta
Classifier: License :: OSI Approved :: MIT License
Classifier: Programming Language :: Python :: 3.6
Classifier: Intended Audience :: Science/Research
Classifier: Topic :: Scientific/Engineering :: Information Analysis
Requires-Dist: numpy
Requires-Dist: scipy
Requires-Dist: networkx
Requires-Dist: mpmath
Requires-Dist: python-igraph
